{
  "_class": "symbolMaster",
  "allowsOverrides": true,
  "backgroundColor": {
    "_class": "color",
    "alpha": 1,
    "blue": 1,
    "green": 1,
    "red": 1
  },
  "booleanOperation": -1,
  "changeIdentifier": 882,
  "clippingMaskMode": 0,
  "do_objectID": "4E275203-E97D-4141-A2C4-06CCA1277BDF",
  "exportOptions": {
    "_class": "exportOptions",
    "exportFormats": [
      {
        "_class": "exportFormat",
        "absoluteSize": 0,
        "fileFormat": "png",
        "name": "",
        "namingScheme": 0,
        "scale": 1,
        "visibleScaleType": 0
      }
    ],
    "includedLayerIds": [
    ],
    "layerOptions": 0,
    "shouldTrim": false
  },
  "frame": {
    "_class": "rect",
    "constrainProportions": false,
    "height": 96,
    "width": 320,
    "x": 1906,
    "y": -484
  },
  "groupLayout": {
    "_class": "MSImmutableFreeformGroupLayout"
  },
  "hasBackgroundColor": false,
  "hasClickThrough": false,
  "hasClippingMask": false,
  "horizontalRulerData": {
    "_class": "rulerData",
    "base": 0,
    "guides": [
    ]
  },
  "includeBackgroundColorInExport": true,
  "includeBackgroundColorInInstance": true,
  "includeInCloudUpload": true,
  "isFixedToViewport": false,
  "isFlippedHorizontal": false,
  "isFlippedVertical": false,
  "isFlowHome": false,
  "isLocked": false,
  "isVisible": true,
  "layerListExpandedType": 2,
  "layers": [
    {
      "class": "symbolInstance",
      "id": "850CAA32-F8FA-42F8-A909-72900437D591"
    },
    {
      "class": "text",
      "id": "3BA5D53B-137D-4702-842E-6E01142ED974"
    },
    {
      "class": "text",
      "id": "0CED259F-5FCF-43E8-BA6D-F7AC8C953C27"
    }
  ],
  "name": "misc / textfield / before",
  "nameIsFixed": true,
  "overrideProperties": [
    {
      "_class": "MSImmutableOverrideProperty",
      "canOverride": true,
      "overrideName": "3BA5D53B-137D-4702-842E-6E01142ED974_textStyle"
    },
    {
      "_class": "MSImmutableOverrideProperty",
      "canOverride": true,
      "overrideName": "0CED259F-5FCF-43E8-BA6D-F7AC8C953C27_textStyle"
    },
    {
      "_class": "MSImmutableOverrideProperty",
      "canOverride": true,
      "overrideName": "3BA5D53B-137D-4702-842E-6E01142ED974_stringValue"
    },
    {
      "_class": "MSImmutableOverrideProperty",
      "canOverride": true,
      "overrideName": "0CED259F-5FCF-43E8-BA6D-F7AC8C953C27_stringValue"
    },
    {
      "_class": "MSImmutableOverrideProperty",
      "canOverride": true,
      "overrideName": "850CAA32-F8FA-42F8-A909-72900437D591_symbolID"
    }
  ],
  "presetDictionary": {
  },
  "resizesContent": true,
  "resizingConstraint": 63,
  "resizingType": 0,
  "rotation": 0,
  "shouldBreakMaskChain": true,
  "style": {
    "_class": "style",
    "blur": {
      "_class": "blur",
      "center": "{0.5, 0.5}",
      "isEnabled": false,
      "motionAngle": 0,
      "radius": 10,
      "saturation": 1,
      "type": 0
    },
    "borderOptions": {
      "_class": "borderOptions",
      "dashPattern": [
      ],
      "isEnabled": true,
      "lineCapStyle": 0,
      "lineJoinStyle": 0
    },
    "borders": [
    ],
    "colorControls": {
      "_class": "colorControls",
      "brightness": 0,
      "contrast": 1,
      "hue": 0,
      "isEnabled": false,
      "saturation": 1
    },
    "contextSettings": {
      "_class": "graphicsContextSettings",
      "blendMode": 0,
      "opacity": 1
    },
    "do_objectID": "43F4C18E-766D-4CBF-85A7-4847D4340114",
    "endMarkerType": 0,
    "fills": [
    ],
    "innerShadows": [
    ],
    "miterLimit": 10,
    "shadows": [
    ],
    "startMarkerType": 0,
    "windingRule": 1
  },
  "symbolID": "8F72B7D7-5759-48E5-9361-D9DFAE33D15F",
  "verticalRulerData": {
    "_class": "rulerData",
    "base": 0,
    "guides": [
    ]
  }
}